{"@context":"https://iiif.io/api/presentation/3/context.json","id":"https://canopy-iiif.github.io/canopy-iiif/api/facet/subject/rye.json","type":"Collection","label":{"none":["Rye"]},"items":[{"id":"https://digital.lib.utk.edu/assemble/manifest/wcc/345","type":"Manifest","label":{"none":["Rye field and Twenty Mile Range from summit of Big Bald"]},"thumbnail":[{"id":"https://digital.lib.utk.edu/iiif/2/collections~islandora~object~wcc%3A345~datastream~JP2/full/691,433/0/default.jpg","width":691,"height":433,"type":"Image","format":"image/jpeg","service":[{"@id":"https://digital.lib.utk.edu/iiif/2/collections~islandora~object~wcc%3A345~datastream~JP2","@type":"http://iiif.io/api/image/2/context.json","profile":"http://iiif.io/api/image/2/level2.json"}]}],"homepage":[{"id":"https://canopy-iiif.github.io/canopy-iiif/works/rye-field-and-twenty-mile-range-from-summit-of-big-bald","type":"Text","label":{"none":["Rye field and Twenty Mile Range from summit of Big Bald"]}}]}],"partOf":[{"id":"https://canopy-iiif.github.io/canopy-iiif/api/facet/subject.json","type":"Collection"}],"summary":{"none":["Subject"]},"homepage":[{"id":"https://canopy-iiif.github.io/canopy-iiif/search?subject=rye","type":"Text","label":{"none":["Rye"]}}]}