{"@context":"https://iiif.io/api/presentation/3/context.json","id":"https://canopy-iiif.github.io/canopy-iiif/api/facet/dimensions/186-x-12-cm-image-size-23-x-16-cm-plate-size.json","type":"Collection","label":{"none":["18.6 x 12 cm [image size], 23 x 16 cm [plate size]"]},"items":[{"id":"https://api.dc.library.northwestern.edu/api/v2/works/88fe9ebd-0a0b-4e24-99a6-75f408532e64?as=iiif","type":"Manifest","label":{"none":["Mnáshwai - Wishham"]},"thumbnail":[{"id":"https://api.dc.library.northwestern.edu/api/v2/works/88fe9ebd-0a0b-4e24-99a6-75f408532e64/thumbnail","type":"Image","format":"image/jpeg","height":300,"width":300}],"homepage":[{"id":"https://canopy-iiif.github.io/canopy-iiif/works/mnashwai-wishham","type":"Text","label":{"none":["Mnáshwai - Wishham"]}}]},{"id":"https://api.dc.library.northwestern.edu/api/v2/works/a9b7caf8-b77f-41d2-bba6-c8d03cd6bbc9?as=iiif","type":"Manifest","label":{"none":["Wishham Man"]},"thumbnail":[{"id":"https://api.dc.library.northwestern.edu/api/v2/works/a9b7caf8-b77f-41d2-bba6-c8d03cd6bbc9/thumbnail","type":"Image","format":"image/jpeg","height":300,"width":300}],"homepage":[{"id":"https://canopy-iiif.github.io/canopy-iiif/works/wishham-man","type":"Text","label":{"none":["Wishham Man"]}}]}],"partOf":[{"id":"https://canopy-iiif.github.io/canopy-iiif/api/facet/dimensions.json","type":"Collection"}],"summary":{"none":["Dimensions"]},"homepage":[{"id":"https://canopy-iiif.github.io/canopy-iiif/search?dimensions=186-x-12-cm-image-size-23-x-16-cm-plate-size","type":"Text","label":{"none":["18.6 x 12 cm [image size], 23 x 16 cm [plate size]"]}}]}