{"@context":"https://iiif.io/api/presentation/3/context.json","id":"https://canopy-iiif.github.io/canopy-iiif/api/facet/date/2007.json","type":"Collection","label":{"none":["2007"]},"items":[{"id":"https://cdm17217.contentdm.oclc.org/iiif/maps:4989/manifest.json","type":"Manifest","label":{"none":["2007 Monroe County highway map"]},"thumbnail":[{"id":"https://cdm17217.contentdm.oclc.org/iiif/2/maps:4989/full/382,/0/default.jpg","type":"Image","format":"image/jpeg","width":382,"height":173}],"homepage":[{"id":"https://canopy-iiif.github.io/canopy-iiif/works/2007-monroe-county-highway-map","type":"Text","label":{"none":["2007 Monroe County highway map"]}}]}],"partOf":[{"id":"https://canopy-iiif.github.io/canopy-iiif/api/facet/date.json","type":"Collection"}],"summary":{"none":["Date"]},"homepage":[{"id":"https://canopy-iiif.github.io/canopy-iiif/search?date=2007","type":"Text","label":{"none":["2007"]}}]}