{"@context":"https://iiif.io/api/presentation/3/context.json","id":"https://canopy-iiif.github.io/canopy-iiif/api/facet/date/aug-20-1886.json","type":"Collection","label":{"none":["Aug 20, 1886"]},"items":[{"id":"https://digital.lib.utk.edu/assemble/manifest/wcc/314","type":"Manifest","label":{"none":["King's cabin. Mt. Nebo"]},"thumbnail":[{"id":"https://digital.lib.utk.edu/iiif/2/collections~islandora~object~wcc%3A314~datastream~JP2/full/438,365/0/default.jpg","width":438,"height":365,"type":"Image","format":"image/jpeg","service":[{"@id":"https://digital.lib.utk.edu/iiif/2/collections~islandora~object~wcc%3A314~datastream~JP2","@type":"http://iiif.io/api/image/2/context.json","profile":"http://iiif.io/api/image/2/level2.json"}]}],"homepage":[{"id":"https://canopy-iiif.github.io/canopy-iiif/works/kings-cabin-mt-nebo","type":"Text","label":{"none":["King's cabin. Mt. Nebo"]}}]},{"id":"https://digital.lib.utk.edu/assemble/manifest/wcc/318","type":"Manifest","label":{"none":["Neubern's Mill pond below Little River Gap."]},"thumbnail":[{"id":"https://digital.lib.utk.edu/iiif/2/collections~islandora~object~wcc%3A318~datastream~JP2/full/691,428/0/default.jpg","width":691,"height":428,"type":"Image","format":"image/jpeg","service":[{"@id":"https://digital.lib.utk.edu/iiif/2/collections~islandora~object~wcc%3A318~datastream~JP2","@type":"http://iiif.io/api/image/2/context.json","profile":"http://iiif.io/api/image/2/level2.json"}]}],"homepage":[{"id":"https://canopy-iiif.github.io/canopy-iiif/works/neuberns-mill-pond-below-little-river-gap","type":"Text","label":{"none":["Neubern's Mill pond below Little River Gap."]}}]},{"id":"https://digital.lib.utk.edu/assemble/manifest/wcc/316","type":"Manifest","label":{"none":["Neubern's Mills and Dam Little River below Gap."]},"thumbnail":[{"id":"https://digital.lib.utk.edu/iiif/2/collections~islandora~object~wcc%3A316~datastream~JP2/full/693,421/0/default.jpg","width":693,"height":421,"type":"Image","format":"image/jpeg","service":[{"@id":"https://digital.lib.utk.edu/iiif/2/collections~islandora~object~wcc%3A316~datastream~JP2","@type":"http://iiif.io/api/image/2/context.json","profile":"http://iiif.io/api/image/2/level2.json"}]}],"homepage":[{"id":"https://canopy-iiif.github.io/canopy-iiif/works/neuberns-mills-and-dam-little-river-below-gap","type":"Text","label":{"none":["Neubern's Mills and Dam Little River below Gap."]}}]}],"partOf":[{"id":"https://canopy-iiif.github.io/canopy-iiif/api/facet/date.json","type":"Collection"}],"summary":{"none":["Date"]},"homepage":[{"id":"https://canopy-iiif.github.io/canopy-iiif/search?date=aug-20-1886","type":"Text","label":{"none":["Aug 20, 1886"]}}]}