{"@context":"https://iiif.io/api/presentation/3/context.json","id":"https://canopy-iiif.github.io/canopy-iiif/api/facet/place/university-of-tennessee.json","type":"Collection","label":{"none":["University of Tennessee"]},"items":[{"id":"https://digital.lib.utk.edu/assemble/manifest/wcc/356","type":"Manifest","label":{"none":["University of E. Tennessee - Knoxville"]},"thumbnail":[{"id":"https://digital.lib.utk.edu/iiif/2/collections~islandora~object~wcc%3A356~datastream~JP2/full/431,352/0/default.jpg","width":431,"height":352,"type":"Image","format":"image/jpeg","service":[{"@id":"https://digital.lib.utk.edu/iiif/2/collections~islandora~object~wcc%3A356~datastream~JP2","@type":"http://iiif.io/api/image/2/context.json","profile":"http://iiif.io/api/image/2/level2.json"}]}],"homepage":[{"id":"https://canopy-iiif.github.io/canopy-iiif/works/university-of-e-tennessee-knoxville","type":"Text","label":{"none":["University of E. Tennessee - Knoxville"]}}]}],"partOf":[{"id":"https://canopy-iiif.github.io/canopy-iiif/api/facet/place.json","type":"Collection"}],"summary":{"none":["Place"]},"homepage":[{"id":"https://canopy-iiif.github.io/canopy-iiif/search?place=university-of-tennessee","type":"Text","label":{"none":["University of Tennessee"]}}]}